pmworker/__init__.py
pmworker/celery.py
pmworker/convert.py
pmworker/document_file.py
pmworker/endpoint.py
pmworker/exceptions.py
pmworker/mime.py
pmworker/pdfinfo.py
pmworker/settings.py
pmworker/shortcuts.py
pmworker/step.py
pmworker/storage.py
pmworker/tasks.py
pmworker/wrapper.py
pmworker-1.0.0.dist-info/LICENSE
pmworker-1.0.0.dist-info/METADATA
pmworker-1.0.0.dist-info/WHEEL
pmworker-1.0.0.dist-info/top_level.txt
pmworker-1.0.0.dist-info/RECORD
