Metadata-Version: 2.1
Name: pmworker
Version: 1.0.0
Summary: Papermerge worker - extract OCR text documents
Home-page: https://github.com/ciur/papermerge-worker
Author: Eugen Ciur
Author-email: eugen@papermerge.com
License: Proprietary
Keywords: tesseract documentation tutorial
Platform: UNKNOWN
Classifier: Programming Language :: Python :: 3
Classifier: License :: OSI Approved :: Apache Software License
Classifier: Operating System :: OS Independent
Requires-Python: >=3.6
